MANIFEST.in
README.md
requirements.txt
requirements_api.txt
setup.py
Envoy_ChatGPT.egg-info/PKG-INFO
Envoy_ChatGPT.egg-info/SOURCES.txt
Envoy_ChatGPT.egg-info/dependency_links.txt
Envoy_ChatGPT.egg-info/entry_points.txt
Envoy_ChatGPT.egg-info/requires.txt
Envoy_ChatGPT.egg-info/top_level.txt
src/envoy/__init__.py
src/envoy/__main__.py
src/envoy/cloud_launcher.py
src/envoy/launcher.py
src/envoy/py.typed
src/envoy/bots/__init__.py
src/envoy/bots/legacy.py
src/envoy/bots/server.py
src/envoy/exts/__init__.py
src/envoy/exts/config.py
src/envoy/exts/hooks.py
src/envoy/exts/sentry.py
src/envoy/exts/token.py
src/envoy/flask/static/apple-touch-icon.png
src/envoy/flask/static/favicon-16x16.png
src/envoy/flask/static/favicon-32x32.png
src/envoy/flask/static/_next/static/chunks/113-23682f80a24dd00d.js
src/envoy/flask/static/_next/static/chunks/14-0cb0d20affbd720d.js
src/envoy/flask/static/_next/static/chunks/174-bd28069f281ef76f.js
src/envoy/flask/static/_next/static/chunks/1f110208-44a6f43ddc5e9011.js
src/envoy/flask/static/_next/static/chunks/264-13e92c51b0315184.js
src/envoy/flask/static/_next/static/chunks/360-442b869f1ba4bb1b.js
src/envoy/flask/static/_next/static/chunks/424-d1d3bfe6a3ca6c4a.js
src/envoy/flask/static/_next/static/chunks/554.9b8bfd0762461d74.js
src/envoy/flask/static/_next/static/chunks/68a27ff6-1185184b61bc22d0.js
src/envoy/flask/static/_next/static/chunks/762-222df1028c0c1555.js
src/envoy/flask/static/_next/static/chunks/949.1a6eb804b5e91f61.js
src/envoy/flask/static/_next/static/chunks/bd26816a-981e1ddc27b37cc6.js
src/envoy/flask/static/_next/static/chunks/framework-7a789ee31d2a7534.js
src/envoy/flask/static/_next/static/chunks/main-149b337e061b4d04.js
src/envoy/flask/static/_next/static/chunks/polyfills-c67a75d1b6f99dc8.js
src/envoy/flask/static/_next/static/chunks/webpack-c9a868e8e0796ec6.js
src/envoy/flask/static/_next/static/chunks/pages/_app-aaa11de1926dcafe.js
src/envoy/flask/static/_next/static/chunks/pages/_error-786d27d84962122a.js
src/envoy/flask/static/_next/static/chunks/pages/chat/[[...chatId]]-76751174916fa3f7.js
src/envoy/flask/static/_next/static/css/ac221fb2caad35a6.css
src/envoy/flask/static/_next/static/olf4sv64FWIcQ_zCGl90t/_buildManifest.js
